<?xml version="1.0"?>
<!DOCTYPE TimeML SYSTEM "TimeML.dtd">
<TimeML>
Aparentemente imparável nos seus projectos de expansão (para grande dor-de-cabeça das marcas europeias) o anúncio da Honda surgiu <TIMEX3 tid="t4" type="DURATION" value="P1W">uma semana</TIMEX3> depois do acordo conseguido entre o Japão e a Comunidade Europeia para a abertura gradual do mercado aos carros nipónicos a partir de <TIMEX3 tid="t1" type="DATE" value="1992">1992</TIMEX3>, e <TIMEX3 tid="t5" type="DURATION" value="P2D">dois dias</TIMEX3> depois da morte do seu «Oyaji-san» (o grande pai), o homem que via na Europa o grande mercado a conquistar.
Soichiro Honda foi o homem que construiu um império, que encarna o renascimento da indústria japonesa no pós-guerra, desde a pequena fábrica de motocicletas, em <TIMEX3 tid="t2" type="DATE" value="1947">1947</TIMEX3>, ao grupo que factura <TIMEX3 tid="t3" type="DATE" value="2017-09-27">hoje</TIMEX3> 4,5 mil milhões de contos e tem 13 milhões de contos de lucros.

</TimeML>

